[
{
  "directory": "/home/student/hw4/wet/build",
  "command": "/usr/bin/x86_64-linux-gnu-g++-7   -g -o CMakeFiles/ariel.dir/os_hw4_part3_tests-main/test.cpp.o -c /home/student/hw4/wet/os_hw4_part3_tests-main/test.cpp",
  "file": "/home/student/hw4/wet/os_hw4_part3_tests-main/test.cpp"
},
{
  "directory": "/home/student/hw4/wet/build",
  "command": "/usr/bin/x86_64-linux-gnu-g++-7   -g -o CMakeFiles/test_3.dir/test_3.cpp.o -c /home/student/hw4/wet/test_3.cpp",
  "file": "/home/student/hw4/wet/test_3.cpp"
}
]